justsendmail.py
justsendmail-4.3.dist-info/LICENSE
justsendmail-4.3.dist-info/METADATA
justsendmail-4.3.dist-info/WHEEL
justsendmail-4.3.dist-info/entry_points.txt
justsendmail-4.3.dist-info/top_level.txt
justsendmail-4.3.dist-info/RECORD
